agents/__init__.py
agents/common/__init__.py
agents/common/base_agent.py
agents/common/command_executor.py
agents/common/os_detector.py
agents/linux/__init__.py
agents/linux/linux_agent.py
agents/linux/linux_agent_cli.py
agents/linux/linux_agent_manager.py
agents/linux/linux_rules.py
agents/macos/__init__.py
agents/macos/macos_agent.py
agents/macos/macos_agent_cli.py
agents/macos/macos_agent_manager.py
agents/macos/macos_rules.py
agents/windows/__init__.py
agents/windows/windows_agent.py
agents/windows/windows_agent_cli.py
agents/windows/windows_agent_manager.py
agents/windows/windows_rules.py
core/__init__.py
core/api.py
core/cli.py
core/config.py
core/deep_scanner.py
core/monitoring.py
database/__init__.py
database/manager.py
database/migration.py
database/mongodb_cli.py
database/mongodb_config.py
database/mongodb_manager.py
database/mongodb_schemas.py
policies/__init__.py
policies/engine.py
policies/rules.py
policies/schemas.py
reporting/__init__.py
reporting/generator.py
security/__init__.py
security/auth.py
security/executor.py
security/config/baselines.yaml
security/config/policies.yaml
security/config/settings.yaml
security/enhanced/__init__.py
security/enhanced/secrets_manager.py
security/enhanced/security_config.py
security/enhanced/security_integration.py
security/enhanced/security_monitor.py
security/enhanced/vulnerability_scanner.py
os_forge-0.2.9.dist-info/LICENSE
os_forge-0.2.9.dist-info/METADATA
os_forge-0.2.9.dist-info/WHEEL
os_forge-0.2.9.dist-info/entry_points.txt
os_forge-0.2.9.dist-info/top_level.txt
os_forge-0.2.9.dist-info/RECORD
