Metadata-Version: 2.1
Name: os-forge
Version: 0.2.9
Summary: Multi-Platform System Hardening Tool with NTRO SIH25237 Compliance - 394 Rules for Windows, Linux, and macOS
Author-email: Aayushman <aayushman2702@gmail.com>
Keywords: security,hardening,compliance,cis,benchmark,ntro,sih25237,windows,linux,macos,ubuntu,centos,automation,cybersecurity,infrastructure,audit,remediation,mongodb
Classifier: Development Status :: 4 - Beta
Classifier: Intended Audience :: System Administrators
Classifier: Intended Audience :: Information Technology
Classifier: Topic :: System :: Systems Administration
Classifier: Topic :: Security
Classifier: License :: OSI Approved :: MIT License
Classifier: Programming Language :: Python :: 3
Classifier: Programming Language :: Python :: 3.8
Classifier: Programming Language :: Python :: 3.9
Classifier: Programming Language :: Python :: 3.10
Classifier: Programming Language :: Python :: 3.11
Classifier: Operating System :: OS Independent
Classifier: Environment :: Console
Requires-Python: >=3.8
License-File: LICENSE
Requires-Dist: fastapi>=0.104.1
Requires-Dist: uvicorn>=0.24.0
Requires-Dist: typer>=0.9.0
Requires-Dist: pydantic>=2.5.0
Requires-Dist: pyyaml>=6.0.1
Requires-Dist: jinja2>=3.1.2
Requires-Dist: weasyprint>=60.2
Requires-Dist: python-multipart>=0.0.6
Requires-Dist: psutil>=5.9.6
Requires-Dist: reportlab>=4.0.7
Requires-Dist: cryptography>=3.4.8
Requires-Dist: pymongo>=4.15.0
Requires-Dist: motor>=3.7.0
Requires-Dist: python-dotenv>=1.0.0
Provides-Extra: dev
Requires-Dist: pytest>=7.0.0; extra == "dev"
Requires-Dist: black>=23.0.0; extra == "dev"
Requires-Dist: flake8>=6.0.0; extra == "dev"
Requires-Dist: mypy>=1.0.0; extra == "dev"
Provides-Extra: full
Requires-Dist: psycopg2-binary>=2.9.0; extra == "full"
Requires-Dist: mysql-connector-python>=8.0.0; extra == "full"
